Metadata-Version: 2.1
Name: scons-tool-clang
Version: 0.2.10
Summary: SCons tool for LLVM clang compiler
Home-page: https://github.com/ptomulik/scons-tool-clang
Author: Paweł Tomulik
Author-email: ptomulik@meil.pw.edu.pl
License: UNKNOWN
Platform: UNKNOWN
